jarvis/__init__.py
jarvis/cli.py
jarvis/core/__init__.py
jarvis/core/config_manager.py
jarvis/core/jarvis_engine.py
jarvis/core/plugin_loader.py
jarvis/core/voice_io.py
jarvis/modules/__init__.py
jarvis/modules/ai_functions.py
jarvis/modules/basic_functions.py
jarvis/modules/productivity_functions.py
jarvis/modules/system_functions.py
jarvis/modules/utility_functions.py
jarvis/modules/web_functions.py
jarvis/plugins/__init__.py
jarvis/plugins/sample_plugin.py
shaheen_jarvis-0.3.2.dist-info/METADATA
shaheen_jarvis-0.3.2.dist-info/WHEEL
shaheen_jarvis-0.3.2.dist-info/entry_points.txt
shaheen_jarvis-0.3.2.dist-info/top_level.txt
shaheen_jarvis-0.3.2.dist-info/RECORD
