Metadata-Version: 2.4
Name: shaheen-jarvis
Version: 0.3.2
Summary: A powerful, voice-enabled AI assistant framework with comprehensive speech recognition, natural language processing, and extensive API integrations.
Home-page: https://github.com/hamza-0987/shaheen_jarvis
Author: Engr. Hamza
Classifier: Development Status :: 3 - Alpha
Classifier: Intended Audience :: Developers
Classifier: License :: OSI Approved :: MIT License
Classifier: Operating System :: OS Independent
Classifier: Programming Language :: Python :: 3
Classifier: Programming Language :: Python :: 3.8
Classifier: Programming Language :: Python :: 3.9
Classifier: Programming Language :: Python :: 3.10
Classifier: Programming Language :: Python :: 3.11
Requires-Python: >=3.8
Requires-Dist: requests>=2.28.0
Requires-Dist: pyttsx3>=2.90
Requires-Dist: SpeechRecognition>=3.8.1
Requires-Dist: wikipedia>=1.4.0
Requires-Dist: psutil>=5.9.0
Requires-Dist: gTTS>=2.2.4
Requires-Dist: pyaudio>=0.2.11
Requires-Dist: openai>=0.27.0
Requires-Dist: beautifulsoup4>=4.11.0
Requires-Dist: lxml>=4.9.0
Requires-Dist: PyYAML>=6.0
Requires-Dist: colorama>=0.4.4
Requires-Dist: click>=8.0.0
Requires-Dist: sounddevice>=0.4.0
Provides-Extra: dev
Requires-Dist: pytest>=7.0.0; extra == "dev"
Requires-Dist: pytest-cov>=4.0.0; extra == "dev"
Requires-Dist: black>=22.0.0; extra == "dev"
Requires-Dist: flake8>=5.0.0; extra == "dev"
Requires-Dist: mypy>=0.991; extra == "dev"
Dynamic: author
Dynamic: classifier
Dynamic: description
Dynamic: description-content-type
Dynamic: home-page
Dynamic: provides-extra
Dynamic: requires-dist
Dynamic: requires-python
Dynamic: summary
